pySembrane/__init__.py
pySembrane/calculator.py
pySembrane/simulator.py
pysembrane-0.0.2.dist-info/METADATA
pysembrane-0.0.2.dist-info/WHEEL
pysembrane-0.0.2.dist-info/top_level.txt
pysembrane-0.0.2.dist-info/RECORD
