Metadata-Version: 2.1
Name: pysembrane
Version: 0.0.2
Summary: Python package for membrane based gas separation process simulations
Home-page: https://nahyeonan.github.io/pySembrane
Author: Seongbin Ga
Author-email: sgasga@ulsan.ac.kr
License: UNKNOWN
Platform: UNKNOWN
Requires-Python: >=3.6
Requires-Dist: numpy (>=1.20.0)
Requires-Dist: scipy (>=1.5.0)
Requires-Dist: matplotlib (>=3.0.0)
